{"id":53,"name":"Trigger","displayName":"Shopify","documentation":"","moduleName":"trigger.shopify","serviceTypes":[{"name":"CustomersService","description":"Triggers when a new event related to Shopify customers is received.\nAvailable actions: onCustomersCreate, onCustomersDisable, onCustomersEnable, onCustomersUpdate, and onCustomersMarketingConsentUpdate\n","functions":[{"isRemote":true,"documentation":"","name":"onCustomersCreate","parameters":[{"name":"event","typeName":"record","optional":false,"typeInfo":{"name":"CustomerEvent","orgName":"ballerinax","moduleName":"trigger.shopify","version":"1.0.0"},"displayAnnotation":{},"hasRestType":true,"defaultable":false,"fields":[{"members":[{"typeName":"string","optional":false,"defaultable":false},{"typeName":"()","optional":false,"defaultable":false}],"name":"total_spent","typeName":"union","optional":true,"defaultable":false},{"name":"note","typeName":"union","optional":true,"defaultable":false},{"members":[{"memberType":{"fields":[{"name":"zip","typeName":"union","optional":true,"defaultable":false},{"name":"country","typeName":"union","optional":true,"defaultable":false},{"name":"address2","typeName":"union","optional":true,"defaultable":false},{"name":"city","typeName":"union","optional":true,"defaultable":false},{"name":"address1","typeName":"union","optional":true,"defaultable":false},{"name":"last_name","typeName":"union","optional":true,"defaultable":false},{"name":"province_code","typeName":"union","optional":true,"defaultable":false},{"name":"country_code","typeName":"union","optional":true,"defaultable":false},{"members":[{"typeName":"boolean","optional":false,"defaultable":false},{"typeName":"()","optional":false,"defaultable":false}],"name":"default","typeName":"union","optional":true,"defaultable":false},{"name":"province","typeName":"union","optional":true,"defaultable":false},{"name":"phone","typeName":"union","optional":true,"defaultable":false},{"name":"country_name","typeName":"union","optional":true,"defaultable":false},{"name":"name","typeName":"union","optional":true,"defaultable":false},{"name":"company","typeName":"union","optional":true,"defaultable":false},{"members":[{"typeName":"int","optional":false,"defaultable":false},{"typeName":"()","optional":false,"defaultable":false}],"name":"id","typeName":"union","optional":true,"defaultable":false},{"name":"customer_id","typeName":"union","optional":true,"defaultable":false},{"name":"first_name","typeName":"union","optional":true,"defaultable":false}],"hasRestType":true,"restType":{"typeName":"anydata","optional":false,"defaultable":false},"name":"Address","typeName":"record","optional":false,"typeInfo":{"name":"Address","orgName":"ballerinax","moduleName":"trigger.shopify","version":"1.0.0"},"defaultable":false},"typeName":"array","optional":false,"defaultable":false},{"typeName":"()","optional":false,"defaultable":false}],"name":"addresses","typeName":"union","optional":true,"defaultable":false},{"name":"last_order_name","typeName":"union","optional":true,"defaultable":false},{"name":"last_order_id","typeName":"union","optional":true,"defaultable":false},{"name":"tax_exempt","typeName":"union","optional":true,"defaultable":false},{"name":"created_at","typeName":"union","optional":true,"defaultable":false},{"name":"last_name","typeName":"union","optional":true,"defaultable":false},{"name":"multipass_identifier","typeName":"union","optional":true,"defaultable":false},{"name":"verified_email","typeName":"union","optional":true,"defaultable":false},{"name":"tags","typeName":"union","optional":true,"defaultable":false},{"name":"accepts_marketing_updated_at","typeName":"union","optional":true,"defaultable":false},{"name":"orders_count","typeName":"union","optional":true,"defaultable":false},{"members":[{"fields":[{"name":"consent_updated_at","typeName":"union","optional":true,"defaultable":false},{"name":"consent_collected_from","typeName":"union","optional":true,"defaultable":false},{"name":"state","typeName":"union","optional":true,"defaultable":false},{"name":"opt_in_level","typeName":"union","optional":true,"defaultable":false}],"hasRestType":true,"restType":{"typeName":"anydata","optional":false,"defaultable":false},"name":"SmsMarketingConsent","typeName":"record","optional":false,"typeInfo":{"name":"SmsMarketingConsent","orgName":"ballerinax","moduleName":"trigger.shopify","version":"1.0.0"},"defaultable":false},{"typeName":"()","optional":false,"defaultable":false}],"name":"sms_marketing_consent","typeName":"union","optional":true,"defaultable":false},{"name":"updated_at","typeName":"union","optional":true,"defaultable":false},{"name":"accepts_marketing","typeName":"union","optional":true,"defaultable":false},{"name":"phone","typeName":"union","optional":true,"defaultable":false},{"name":"admin_graphql_api_id","typeName":"union","optional":true,"defaultable":false},{"name":"currency","typeName":"union","optional":true,"defaultable":false},{"name":"id","typeName":"union","optional":true,"defaultable":false},{"name":"state","typeName":"union","optional":true,"defaultable":false},{"name":"marketing_opt_in_level","typeName":"union","optional":true,"defaultable":false},{"name":"first_name","typeName":"union","optional":true,"defaultable":false},{"name":"email","typeName":"union","optional":true,"defaultable":false}],"restType":{"typeName":"anydata","optional":false,"defaultable":false}}],"returnType":{"typeName":"error","optional":true,"displayAnnotation":{},"defaultable":false},"displayAnnotation":{}},{"isRemote":true,"documentation":"","name":"onCustomersDisable","parameters":[{"name":"event","typeName":"record","optional":false,"typeInfo":{"name":"CustomerEvent","orgName":"ballerinax","moduleName":"trigger.shopify","version":"1.0.0"},"displayAnnotation":{},"hasRestType":true,"defaultable":false,"fields":[{"members":[{"typeName":"string","optional":false,"defaultable":false},{"typeName":"()","optional":false,"defaultable":false}],"name":"total_spent","typeName":"union","optional":true,"defaultable":false},{"name":"note","typeName":"union","optional":true,"defaultable":false},{"members":[{"memberType":{"fields":[{"name":"zip","typeName":"union","optional":true,"defaultable":false},{"name":"country","typeName":"union","optional":true,"defaultable":false},{"name":"address2","typeName":"union","optional":true,"defaultable":false},{"name":"city","typeName":"union","optional":true,"defaultable":false},{"name":"address1","typeName":"union","optional":true,"defaultable":false},{"name":"last_name","typeName":"union","optional":true,"defaultable":false},{"name":"province_code","typeName":"union","optional":true,"defaultable":false},{"name":"country_code","typeName":"union","optional":true,"defaultable":false},{"members":[{"typeName":"boolean","optional":false,"defaultable":false},{"typeName":"()","optional":false,"defaultable":false}],"name":"default","typeName":"union","optional":true,"defaultable":false},{"name":"province","typeName":"union","optional":true,"defaultable":false},{"name":"phone","typeName":"union","optional":true,"defaultable":false},{"name":"country_name","typeName":"union","optional":true,"defaultable":false},{"name":"name","typeName":"union","optional":true,"defaultable":false},{"name":"company","typeName":"union","optional":true,"defaultable":false},{"members":[{"typeName":"int","optional":false,"defaultable":false},{"typeName":"()","optional":false,"defaultable":false}],"name":"id","typeName":"union","optional":true,"defaultable":false},{"name":"customer_id","typeName":"union","optional":true,"defaultable":false},{"name":"first_name","typeName":"union","optional":true,"defaultable":false}],"hasRestType":true,"restType":{"typeName":"anydata","optional":false,"defaultable":false},"name":"Address","typeName":"record","optional":false,"typeInfo":{"name":"Address","orgName":"ballerinax","moduleName":"trigger.shopify","version":"1.0.0"},"defaultable":false},"typeName":"array","optional":false,"defaultable":false},{"typeName":"()","optional":false,"defaultable":false}],"name":"addresses","typeName":"union","optional":true,"defaultable":false},{"name":"last_order_name","typeName":"union","optional":true,"defaultable":false},{"name":"last_order_id","typeName":"union","optional":true,"defaultable":false},{"name":"tax_exempt","typeName":"union","optional":true,"defaultable":false},{"name":"created_at","typeName":"union","optional":true,"defaultable":false},{"name":"last_name","typeName":"union","optional":true,"defaultable":false},{"name":"multipass_identifier","typeName":"union","optional":true,"defaultable":false},{"name":"verified_email","typeName":"union","optional":true,"defaultable":false},{"name":"tags","typeName":"union","optional":true,"defaultable":false},{"name":"accepts_marketing_updated_at","typeName":"union","optional":true,"defaultable":false},{"name":"orders_count","typeName":"union","optional":true,"defaultable":false},{"members":[{"fields":[{"name":"consent_updated_at","typeName":"union","optional":true,"defaultable":false},{"name":"consent_collected_from","typeName":"union","optional":true,"defaultable":false},{"name":"state","typeName":"union","optional":true,"defaultable":false},{"name":"opt_in_level","typeName":"union","optional":true,"defaultable":false}],"hasRestType":true,"restType":{"typeName":"anydata","optional":false,"defaultable":false},"name":"SmsMarketingConsent","typeName":"record","optional":false,"typeInfo":{"name":"SmsMarketingConsent","orgName":"ballerinax","moduleName":"trigger.shopify","version":"1.0.0"},"defaultable":false},{"typeName":"()","optional":false,"defaultable":false}],"name":"sms_marketing_consent","typeName":"union","optional":true,"defaultable":false},{"name":"updated_at","typeName":"union","optional":true,"defaultable":false},{"name":"accepts_marketing","typeName":"union","optional":true,"defaultable":false},{"name":"phone","typeName":"union","optional":true,"defaultable":false},{"name":"admin_graphql_api_id","typeName":"union","optional":true,"defaultable":false},{"name":"currency","typeName":"union","optional":true,"defaultable":false},{"name":"id","typeName":"union","optional":true,"defaultable":false},{"name":"state","typeName":"union","optional":true,"defaultable":false},{"name":"marketing_opt_in_level","typeName":"union","optional":true,"defaultable":false},{"name":"first_name","typeName":"union","optional":true,"defaultable":false},{"name":"email","typeName":"union","optional":true,"defaultable":false}],"restType":{"typeName":"anydata","optional":false,"defaultable":false}}],"returnType":{"typeName":"error","optional":true,"displayAnnotation":{},"defaultable":false},"displayAnnotation":{}},{"isRemote":true,"documentation":"","name":"onCustomersEnable","parameters":[{"name":"event","typeName":"record","optional":false,"typeInfo":{"name":"CustomerEvent","orgName":"ballerinax","moduleName":"trigger.shopify","version":"1.0.0"},"displayAnnotation":{},"hasRestType":true,"defaultable":false,"fields":[{"members":[{"typeName":"string","optional":false,"defaultable":false},{"typeName":"()","optional":false,"defaultable":false}],"name":"total_spent","typeName":"union","optional":true,"defaultable":false},{"name":"note","typeName":"union","optional":true,"defaultable":false},{"members":[{"memberType":{"fields":[{"name":"zip","typeName":"union","optional":true,"defaultable":false},{"name":"country","typeName":"union","optional":true,"defaultable":false},{"name":"address2","typeName":"union","optional":true,"defaultable":false},{"name":"city","typeName":"union","optional":true,"defaultable":false},{"name":"address1","typeName":"union","optional":true,"defaultable":false},{"name":"last_name","typeName":"union","optional":true,"defaultable":false},{"name":"province_code","typeName":"union","optional":true,"defaultable":false},{"name":"country_code","typeName":"union","optional":true,"defaultable":false},{"members":[{"typeName":"boolean","optional":false,"defaultable":false},{"typeName":"()","optional":false,"defaultable":false}],"name":"default","typeName":"union","optional":true,"defaultable":false},{"name":"province","typeName":"union","optional":true,"defaultable":false},{"name":"phone","typeName":"union","optional":true,"defaultable":false},{"name":"country_name","typeName":"union","optional":true,"defaultable":false},{"name":"name","typeName":"union","optional":true,"defaultable":false},{"name":"company","typeName":"union","optional":true,"defaultable":false},{"members":[{"typeName":"int","optional":false,"defaultable":false},{"typeName":"()","optional":false,"defaultable":false}],"name":"id","typeName":"union","optional":true,"defaultable":false},{"name":"customer_id","typeName":"union","optional":true,"defaultable":false},{"name":"first_name","typeName":"union","optional":true,"defaultable":false}],"hasRestType":true,"restType":{"typeName":"anydata","optional":false,"defaultable":false},"name":"Address","typeName":"record","optional":false,"typeInfo":{"name":"Address","orgName":"ballerinax","moduleName":"trigger.shopify","version":"1.0.0"},"defaultable":false},"typeName":"array","optional":false,"defaultable":false},{"typeName":"()","optional":false,"defaultable":false}],"name":"addresses","typeName":"union","optional":true,"defaultable":false},{"name":"last_order_name","typeName":"union","optional":true,"defaultable":false},{"name":"last_order_id","typeName":"union","optional":true,"defaultable":false},{"name":"tax_exempt","typeName":"union","optional":true,"defaultable":false},{"name":"created_at","typeName":"union","optional":true,"defaultable":false},{"name":"last_name","typeName":"union","optional":true,"defaultable":false},{"name":"multipass_identifier","typeName":"union","optional":true,"defaultable":false},{"name":"verified_email","typeName":"union","optional":true,"defaultable":false},{"name":"tags","typeName":"union","optional":true,"defaultable":false},{"name":"accepts_marketing_updated_at","typeName":"union","optional":true,"defaultable":false},{"name":"orders_count","typeName":"union","optional":true,"defaultable":false},{"members":[{"fields":[{"name":"consent_updated_at","typeName":"union","optional":true,"defaultable":false},{"name":"consent_collected_from","typeName":"union","optional":true,"defaultable":false},{"name":"state","typeName":"union","optional":true,"defaultable":false},{"name":"opt_in_level","typeName":"union","optional":true,"defaultable":false}],"hasRestType":true,"restType":{"typeName":"anydata","optional":false,"defaultable":false},"name":"SmsMarketingConsent","typeName":"record","optional":false,"typeInfo":{"name":"SmsMarketingConsent","orgName":"ballerinax","moduleName":"trigger.shopify","version":"1.0.0"},"defaultable":false},{"typeName":"()","optional":false,"defaultable":false}],"name":"sms_marketing_consent","typeName":"union","optional":true,"defaultable":false},{"name":"updated_at","typeName":"union","optional":true,"defaultable":false},{"name":"accepts_marketing","typeName":"union","optional":true,"defaultable":false},{"name":"phone","typeName":"union","optional":true,"defaultable":false},{"name":"admin_graphql_api_id","typeName":"union","optional":true,"defaultable":false},{"name":"currency","typeName":"union","optional":true,"defaultable":false},{"name":"id","typeName":"union","optional":true,"defaultable":false},{"name":"state","typeName":"union","optional":true,"defaultable":false},{"name":"marketing_opt_in_level","typeName":"union","optional":true,"defaultable":false},{"name":"first_name","typeName":"union","optional":true,"defaultable":false},{"name":"email","typeName":"union","optional":true,"defaultable":false}],"restType":{"typeName":"anydata","optional":false,"defaultable":false}}],"returnType":{"typeName":"error","optional":true,"displayAnnotation":{},"defaultable":false},"displayAnnotation":{}},{"isRemote":true,"documentation":"","name":"onCustomersUpdate","parameters":[{"name":"event","typeName":"record","optional":false,"typeInfo":{"name":"CustomerEvent","orgName":"ballerinax","moduleName":"trigger.shopify","version":"1.0.0"},"displayAnnotation":{},"hasRestType":true,"defaultable":false,"fields":[{"members":[{"typeName":"string","optional":false,"defaultable":false},{"typeName":"()","optional":false,"defaultable":false}],"name":"total_spent","typeName":"union","optional":true,"defaultable":false},{"name":"note","typeName":"union","optional":true,"defaultable":false},{"members":[{"memberType":{"fields":[{"name":"zip","typeName":"union","optional":true,"defaultable":false},{"name":"country","typeName":"union","optional":true,"defaultable":false},{"name":"address2","typeName":"union","optional":true,"defaultable":false},{"name":"city","typeName":"union","optional":true,"defaultable":false},{"name":"address1","typeName":"union","optional":true,"defaultable":false},{"name":"last_name","typeName":"union","optional":true,"defaultable":false},{"name":"province_code","typeName":"union","optional":true,"defaultable":false},{"name":"country_code","typeName":"union","optional":true,"defaultable":false},{"members":[{"typeName":"boolean","optional":false,"defaultable":false},{"typeName":"()","optional":false,"defaultable":false}],"name":"default","typeName":"union","optional":true,"defaultable":false},{"name":"province","typeName":"union","optional":true,"defaultable":false},{"name":"phone","typeName":"union","optional":true,"defaultable":false},{"name":"country_name","typeName":"union","optional":true,"defaultable":false},{"name":"name","typeName":"union","optional":true,"defaultable":false},{"name":"company","typeName":"union","optional":true,"defaultable":false},{"members":[{"typeName":"int","optional":false,"defaultable":false},{"typeName":"()","optional":false,"defaultable":false}],"name":"id","typeName":"union","optional":true,"defaultable":false},{"name":"customer_id","typeName":"union","optional":true,"defaultable":false},{"name":"first_name","typeName":"union","optional":true,"defaultable":false}],"hasRestType":true,"restType":{"typeName":"anydata","optional":false,"defaultable":false},"name":"Address","typeName":"record","optional":false,"typeInfo":{"name":"Address","orgName":"ballerinax","moduleName":"trigger.shopify","version":"1.0.0"},"defaultable":false},"typeName":"array","optional":false,"defaultable":false},{"typeName":"()","optional":false,"defaultable":false}],"name":"addresses","typeName":"union","optional":true,"defaultable":false},{"name":"last_order_name","typeName":"union","optional":true,"defaultable":false},{"name":"last_order_id","typeName":"union","optional":true,"defaultable":false},{"name":"tax_exempt","typeName":"union","optional":true,"defaultable":false},{"name":"created_at","typeName":"union","optional":true,"defaultable":false},{"name":"last_name","typeName":"union","optional":true,"defaultable":false},{"name":"multipass_identifier","typeName":"union","optional":true,"defaultable":false},{"name":"verified_email","typeName":"union","optional":true,"defaultable":false},{"name":"tags","typeName":"union","optional":true,"defaultable":false},{"name":"accepts_marketing_updated_at","typeName":"union","optional":true,"defaultable":false},{"name":"orders_count","typeName":"union","optional":true,"defaultable":false},{"members":[{"fields":[{"name":"consent_updated_at","typeName":"union","optional":true,"defaultable":false},{"name":"consent_collected_from","typeName":"union","optional":true,"defaultable":false},{"name":"state","typeName":"union","optional":true,"defaultable":false},{"name":"opt_in_level","typeName":"union","optional":true,"defaultable":false}],"hasRestType":true,"restType":{"typeName":"anydata","optional":false,"defaultable":false},"name":"SmsMarketingConsent","typeName":"record","optional":false,"typeInfo":{"name":"SmsMarketingConsent","orgName":"ballerinax","moduleName":"trigger.shopify","version":"1.0.0"},"defaultable":false},{"typeName":"()","optional":false,"defaultable":false}],"name":"sms_marketing_consent","typeName":"union","optional":true,"defaultable":false},{"name":"updated_at","typeName":"union","optional":true,"defaultable":false},{"name":"accepts_marketing","typeName":"union","optional":true,"defaultable":false},{"name":"phone","typeName":"union","optional":true,"defaultable":false},{"name":"admin_graphql_api_id","typeName":"union","optional":true,"defaultable":false},{"name":"currency","typeName":"union","optional":true,"defaultable":false},{"name":"id","typeName":"union","optional":true,"defaultable":false},{"name":"state","typeName":"union","optional":true,"defaultable":false},{"name":"marketing_opt_in_level","typeName":"union","optional":true,"defaultable":false},{"name":"first_name","typeName":"union","optional":true,"defaultable":false},{"name":"email","typeName":"union","optional":true,"defaultable":false}],"restType":{"typeName":"anydata","optional":false,"defaultable":false}}],"returnType":{"typeName":"error","optional":true,"displayAnnotation":{},"defaultable":false},"displayAnnotation":{}},{"isRemote":true,"documentation":"","name":"onCustomersMarketingConsentUpdate","parameters":[{"name":"event","typeName":"record","optional":false,"typeInfo":{"name":"CustomerEvent","orgName":"ballerinax","moduleName":"trigger.shopify","version":"1.0.0"},"displayAnnotation":{},"hasRestType":true,"defaultable":false,"fields":[{"members":[{"typeName":"string","optional":false,"defaultable":false},{"typeName":"()","optional":false,"defaultable":false}],"name":"total_spent","typeName":"union","optional":true,"defaultable":false},{"name":"note","typeName":"union","optional":true,"defaultable":false},{"members":[{"memberType":{"fields":[{"name":"zip","typeName":"union","optional":true,"defaultable":false},{"name":"country","typeName":"union","optional":true,"defaultable":false},{"name":"address2","typeName":"union","optional":true,"defaultable":false},{"name":"city","typeName":"union","optional":true,"defaultable":false},{"name":"address1","typeName":"union","optional":true,"defaultable":false},{"name":"last_name","typeName":"union","optional":true,"defaultable":false},{"name":"province_code","typeName":"union","optional":true,"defaultable":false},{"name":"country_code","typeName":"union","optional":true,"defaultable":false},{"members":[{"typeName":"boolean","optional":false,"defaultable":false},{"typeName":"()","optional":false,"defaultable":false}],"name":"default","typeName":"union","optional":true,"defaultable":false},{"name":"province","typeName":"union","optional":true,"defaultable":false},{"name":"phone","typeName":"union","optional":true,"defaultable":false},{"name":"country_name","typeName":"union","optional":true,"defaultable":false},{"name":"name","typeName":"union","optional":true,"defaultable":false},{"name":"company","typeName":"union","optional":true,"defaultable":false},{"members":[{"typeName":"int","optional":false,"defaultable":false},{"typeName":"()","optional":false,"defaultable":false}],"name":"id","typeName":"union","optional":true,"defaultable":false},{"name":"customer_id","typeName":"union","optional":true,"defaultable":false},{"name":"first_name","typeName":"union","optional":true,"defaultable":false}],"hasRestType":true,"restType":{"typeName":"anydata","optional":false,"defaultable":false},"name":"Address","typeName":"record","optional":false,"typeInfo":{"name":"Address","orgName":"ballerinax","moduleName":"trigger.shopify","version":"1.0.0"},"defaultable":false},"typeName":"array","optional":false,"defaultable":false},{"typeName":"()","optional":false,"defaultable":false}],"name":"addresses","typeName":"union","optional":true,"defaultable":false},{"name":"last_order_name","typeName":"union","optional":true,"defaultable":false},{"name":"last_order_id","typeName":"union","optional":true,"defaultable":false},{"name":"tax_exempt","typeName":"union","optional":true,"defaultable":false},{"name":"created_at","typeName":"union","optional":true,"defaultable":false},{"name":"last_name","typeName":"union","optional":true,"defaultable":false},{"name":"multipass_identifier","typeName":"union","optional":true,"defaultable":false},{"name":"verified_email","typeName":"union","optional":true,"defaultable":false},{"name":"tags","typeName":"union","optional":true,"defaultable":false},{"name":"accepts_marketing_updated_at","typeName":"union","optional":true,"defaultable":false},{"name":"orders_count","typeName":"union","optional":true,"defaultable":false},{"members":[{"fields":[{"name":"consent_updated_at","typeName":"union","optional":true,"defaultable":false},{"name":"consent_collected_from","typeName":"union","optional":true,"defaultable":false},{"name":"state","typeName":"union","optional":true,"defaultable":false},{"name":"opt_in_level","typeName":"union","optional":true,"defaultable":false}],"hasRestType":true,"restType":{"typeName":"anydata","optional":false,"defaultable":false},"name":"SmsMarketingConsent","typeName":"record","optional":false,"typeInfo":{"name":"SmsMarketingConsent","orgName":"ballerinax","moduleName":"trigger.shopify","version":"1.0.0"},"defaultable":false},{"typeName":"()","optional":false,"defaultable":false}],"name":"sms_marketing_consent","typeName":"union","optional":true,"defaultable":false},{"name":"updated_at","typeName":"union","optional":true,"defaultable":false},{"name":"accepts_marketing","typeName":"union","optional":true,"defaultable":false},{"name":"phone","typeName":"union","optional":true,"defaultable":false},{"name":"admin_graphql_api_id","typeName":"union","optional":true,"defaultable":false},{"name":"currency","typeName":"union","optional":true,"defaultable":false},{"name":"id","typeName":"union","optional":true,"defaultable":false},{"name":"state","typeName":"union","optional":true,"defaultable":false},{"name":"marketing_opt_in_level","typeName":"union","optional":true,"defaultable":false},{"name":"first_name","typeName":"union","optional":true,"defaultable":false},{"name":"email","typeName":"union","optional":true,"defaultable":false}],"restType":{"typeName":"anydata","optional":false,"defaultable":false}}],"returnType":{"typeName":"error","optional":true,"displayAnnotation":{},"defaultable":false},"displayAnnotation":{}}],"displayAnnotation":{}}],"listenerParams":[{"name":"listenerConfig","typeName":"record","optional":false,"typeInfo":{"name":"ListenerConfig","orgName":"ballerinax","moduleName":"trigger.shopify","version":"1.0.0"},"displayAnnotation":{},"hasRestType":true,"defaultable":false,"fields":[{"name":"apiSecretKey","typeName":"string","optional":false,"defaultable":false}],"restType":{"typeName":"anydata","optional":false,"defaultable":false}},{"name":"listenOn","typeName":"union","optional":false,"defaultValue":"8090","displayAnnotation":{},"defaultable":true,"members":[{"typeName":"int","optional":false,"defaultable":false},{"fields":[],"name":"Listener","typeName":"object","optional":false,"typeInfo":{"name":"Listener","orgName":"ballerina","moduleName":"http","version":"2.2.2"},"defaultable":false}]}],"listenerProtocol":"http","displayAnnotation":{"label":"Shopify","iconPath":"docs/icon.png"},"package":{"organization":"ballerinax","name":"trigger.shopify","version":"1.0.0","platform":"any","languageSpecificationVersion":"2022R1","URL":"/ballerinax/trigger.shopify/1.0.0","balaVersion":"2.0.0","balaURL":"https://fileserver.dev-central.ballerina.io/2.0/ballerinax/trigger.shopify/1.0.0/ballerinax-trigger.shopify-any-1.0.0.bala?md5=ozWcPb_lloakL7QBLsJpWg&expires=1663765568","digest":"sha-256=87fbaf9508468f7532c8e7b9797b6872df7324d55f7f48f647df0fe3da056105","summary":"Listen to [Shopify Webhook API](https://shopify.dev/apps/webhooks) from Ballerina","readme":"Listen to [Shopify Webhook API](https://shopify.dev/apps/webhooks) from Ballerina\n\n## Package overview\nThe `ballerinax/trigger.shopify` is a [Ballerina](https://ballerina.io/) trigger for Shopify.\nThis package provides the capability to listen to events in Shopify.\n\n### Compatibility\n|                               | Version                        |\n|-------------------------------|--------------------------------|\n| Ballerina Language            | Ballerina Swan Lake 2201.0.4   |\n| Shopify Webhook API           | 2021-10                        |\n\n## Report issues\nTo report bugs, request new features, start new discussions, view project boards, etc., go to the [Ballerina Extended Library repository](https://github.com/ballerina-platform/ballerina-extended-library)\n\n## Useful links\n- Discuss code changes of the Ballerina project in [ballerina-dev@googlegroups.com](mailto:ballerina-dev@googlegroups.com).\n- Chat live with us via our [Slack channel](https://ballerina.io/community/slack/).\n- Post all technical questions on Stack Overflow with the [#ballerina](https://stackoverflow.com/questions/tagged/ballerina) tag","template":false,"licenses":["Apache-2.0"],"authors":["Ballerina"],"sourceCodeLocation":"https://github.com/ballerina-platform/asyncapi-triggers","keywords":["Commerce/eCommerce","Cost/Paid","Trigger"],"ballerinaVersion":"2201.0.4","icon":"https://bcentral-dev-packageicons.azureedge.net/images/ballerinax_trigger.shopify_1.0.0.png","ownerUUID":"b0d77558-9554-4b2e-8211-7f6e2009562d","createdDate":1656998667000,"pullCount":14,"visibility":"public","modules":[{"packageURL":"/ballerinax/trigger.shopify/1.0.0","apiDocURL":"https://dev-lib.ballerina.io/ballerinax/trigger.shopify/1.0.0","name":"trigger.shopify","summary":"The Shopify trigger allows you to listen to [Shopify webhook notifications](https://shopify.dev/apps/webhooks).","readme":"## Overview\nThe Shopify trigger allows you to listen to [Shopify webhook notifications](https://shopify.dev/apps/webhooks).\nYou can use webhook subscriptions to receive notifications about particular events in Shopify shops.\nAfter you've subscribed to a webhook topic, your app can execute code immediately after specific events occur in shops that have your app installed, instead of having to make API calls periodically to check their status.\n\n## Prerequisites\nBefore using this trigger in your Ballerina application, complete the following:\n\n* Create a [Shopify](https://www.shopify.com) account\n\n## Quickstart\nTo use the Shopify trigger in your Ballerina application, update the .bal file as follows:\n\n### Step 1: Import the trigger\nFirst, import `ballerinax/trigger.shopify` module into the Ballerina project as follows.\n```ballerina\n    import ballerinax/trigger.shopify;\n```\n\n### Step 2: Create a new trigger instance\nInitialize the trigger by providing the Shopify API secret key in the listener config and the port number where your trigger will be running. You can also pass a http:Listener instance instead of the port number with the listener config. The Shopify API secret key is viewable under `Webhooks` in the Shopify admin dashboard (if the webhook is created using the dashboard) or under `API credentials` in the Shopify App (if the webhook is created programatically).\n```ballerina\n    shopify:ListenerConfig listenerConfig = {\n        apiSecretKey: \"<SHOPIFY_API_SECRET_KEY>\"\n    };\n    listener shopify:Listener shopifyListener = new(listenerConfig, 8090);\n```\n\nIf you don't provide a port it will use the default port which is 8090.\n```ballerina\n    shopify:ListenerConfig listenerConfig = {\n        apiSecretKey: \"<SHOPIFY_API_SECRET_KEY>\"\n    };\n    listener shopify:Listener shopifyListener = new(listenerConfig);\n```\n\n### Step 3: Run the trigger service\n1. Use the correct service type for the corresponding event channel you are interested, when implementing the service (For example, `shopify:OrdersService`). Now you can implement the trigger remote functions (For example, `onOrdersCreate`, `onOrdersCancelled` etc) supported under this service type. \n\n    Following is an example on how to listen to Shopify order events using the Shopify trigger.\n\n    ```ballerina\n    service shopify:OrdersService on shopifyListener {\n        remote function onOrdersCreate(shopify:OrderEvent event) returns error? {\n            // Write your logic here\n        }\n        remote function onOrdersCancelled(shopify:OrderEvent event) returns error? {\n            // Write your logic here\n        }\n        remote function onOrdersFulfilled(shopify:OrderEvent event) returns error? {\n            // Write your logic here\n        }\n        remote function onOrdersPaid(shopify:OrderEvent event) returns error? {\n            // Write your logic here\n        }\n        remote function onOrdersPartiallyFulfilled(shopify:OrderEvent event) returns error? {\n            // Write your logic here\n        }\n        remote function onOrdersUpdated(shopify:OrderEvent event) returns error? {\n            // Write your logic here\n        }\n    }\n    ```\n\n2. Use `bal run` command to compile and run the Ballerina program. \n\n### Step 4: Subscribe to a webhook topic with the URL of the service\nSubscribe to a webhook topic by following [this guide](https://shopify.dev/apps/webhooks/configuration/https). You can use the `createWebhook` operation of the [Ballerina Shopify Admin connector](https://central.ballerina.io/ballerinax/shopify.admin) to programatically subscribe to a webhook topic. You can also use the Shopify Admin dashboard to manually create a webhook. In your Shopify Admin dashboard, head to `Settings > Notifications` and scroll down to `Webhooks` to create a new webhook. The ballerina service functions will be triggerred everytime a specific event (that you have subscribed) occurs in the shop that have your Shopify app installed.\n\n> **Note**: \n> - Locally, you can use [ngrok](https://ngrok.com/docs) to expose your web service to the internet and to obtain a public URL (For example: 'https://7745640c2478.ngrok.io'). \n> - In Choreo, you can obtain this service URL from the `Invoke URL` section of the `Configure and Deploy` form under `Deploy` view before App deployment.\n> - Add a trailing `/` to the end of public URL if it's not present. "}]},"triggerType":"shopify","httpBased":true}